{"v":"5.7.5","fr":100,"ip":0,"op":400,"w":512,"h":380,"nm":"Comp 1","ddd":0,"assets":[],"layers":[{"ddd":0,"ind":1,"ty":3,"nm":"","sr":1,"ks":{"o":{"a":0,"k":100,"ix":2},"r":{"a":0,"k":0,"ix":2},"p":{"a":0,"k":[202.283,219.483],"ix":2},"a":{"a":0,"k":[50,50],"ix":2},"s":{"a":0,"k":[52,52],"ix":2}},"ao":0,"ip":0,"op":400,"st":0,"bm":0,"hd":false},{"ddd":0,"ind":2,"ty":3,"nm":"","sr":1,"ks":{"o":{"a":0,"k":100,"ix":2},"r":{"a":0,"k":0,"ix":2},"p":{"a":0,"k":[217.271,103.078],"ix":2},"a":{"a":0,"k":[64.554,6.561],"ix":2},"s":{"a":1,"k":[{"t":2,"s":[100,100],"i":{"x":[1],"y":[1]},"o":{"x":[0],"y":[0]}},{"t":202,"s":[100,101],"i":{"x":[1],"y":[1]},"o":{"x":[0],"y":[0]}},{"t":395,"s":[100,100],"i":{"x":[1],"y":[1]},"o":{"x":[0],"y":[0]}}],"ix":2}},"ao":0,"ip":0,"op":400,"st":0,"bm":0,"hd":false,"parent":1},{"ddd":0,"ind":3,"ty":3,"nm":"","sr":1,"ks":{"o":{"a":0,"k":100,"ix":2},"r":{"a":1,"k":[{"t":2,"s":[0],"i":{"x":[1],"y":[1]},"o":{"x":[0],"y":[0]}},{"t":202,"s":[5],"i":{"x":[1],"y":[1]},"o":{"x":[0],"y":[0]}},{"t":395,"s":[0],"i":{"x":[1],"y":[1]},"o":{"x":[0],"y":[0]}}],"ix":2},"p":{"a":0,"k":[-78.814,-149.645],"ix":2},"a":{"a":0,"k":[-78.814,-149.645],"ix":2},"s":{"a":0,"k":[100,100],"ix":2}},"ao":0,"ip":0,"op":400,"st":0,"bm":0,"hd":false,"parent":2},{"ddd":0,"ind":4,"ty":4,"nm":"Group 1","sr":1,"ks":{"o":{"a":0,"k":100,"ix":2},"r":{"a":0,"k":0,"ix":2},"p":{"a":0,"k":[0,0],"ix":2},"a":{"a":0,"k":[0,0],"ix":2},"s":{"a":0,"k":[100,100],"ix":2}},"ao":0,"hd":false,"parent":3,"shapes":[{"ty":"gr","hd":false,"it":[{"ty":"sh","hd":false,"d":1,"ks":{"a":1,"k":[{"t":2,"s":[{"c":false,"v":[[-105.525,-128.014],[-110.127,-84.543],[-111.223,-82.798],[-123.298,-70.743],[-109.145,-69.426],[-104.208,-39.803],[-92.775,-42.268],[-97.954,-52.94],[-97.954,-68.768],[-98.331,-52.185],[-92.602,-45.572],[-86.105,-79.3],[-40.683,-124.393],[-55.729,-170.191]],"i":[[0,0],[0,0],[0.629,-0.375],[2.398,-5.861],[-4.608,0.658],[-5.409,-7.802],[5.934,5.227],[0,4.163],[0,0],[-0.459,-3.431],[-3.092,-0.801],[0,0],[0,0],[0,0]],"o":[[0,0],[-0.071,0.728],[-2.608,1.555],[0,0],[0,0],[6.34,9.144],[-3.124,-2.752],[0,0],[-0.825,8.168],[0.424,3.166],[13.176,3.411],[26.332,-18.432],[22.711,-29.623],[0,0]]}],"i":{"x":[1],"y":[1]},"o":{"x":[0],"y":[0]}},{"t":202,"s":[{"c":false,"v":[[-105.276,-125.168],[-110.127,-84.543],[-111.223,-82.798],[-123.298,-70.743],[-109.145,-69.426],[-104.208,-39.803],[-92.775,-42.268],[-97.954,-52.94],[-97.954,-68.768],[-98.331,-52.185],[-92.602,-45.572],[-86.105,-79.3],[-40.683,-124.393],[-55.729,-170.191]],"i":[[0,0],[0,0],[0.629,-0.375],[2.398,-5.861],[-4.608,0.658],[-5.409,-7.802],[5.934,5.227],[0,4.163],[0,0],[-0.459,-3.431],[-3.092,-0.801],[0,0],[0,0],[0,0]],"o":[[0,0],[-0.071,0.728],[-2.608,1.555],[0,0],[0,0],[6.34,9.144],[-3.124,-2.752],[0,0],[-0.825,8.168],[0.424,3.166],[13.176,3.411],[26.332,-18.432],[22.711,-29.623],[0,0]]}],"i":{"x":[1],"y":[1]},"o":{"x":[0],"y":[0]}},{"t":395,"s":[{"c":false,"v":[[-105.525,-128.014],[-110.127,-84.543],[-111.223,-82.798],[-123.298,-70.743],[-109.145,-69.426],[-104.208,-39.803],[-92.775,-42.268],[-97.954,-52.94],[-97.954,-68.768],[-98.331,-52.185],[-92.602,-45.572],[-86.105,-79.3],[-40.683,-124.393],[-55.729,-170.191]],"i":[[0,0],[0,0],[0.629,-0.375],[2.398,-5.861],[-4.608,0.658],[-5.409,-7.802],[5.934,5.227],[0,4.163],[0,0],[-0.459,-3.431],[-3.092,-0.801],[0,0],[0,0],[0,0]],"o":[[0,0],[-0.071,0.728],[-2.608,1.555],[0,0],[0,0],[6.34,9.144],[-3.124,-2.752],[0,0],[-0.825,8.168],[0.424,3.166],[13.176,3.411],[26.332,-18.432],[22.711,-29.623],[0,0]]}],"i":{"x":[1],"y":[1]},"o":{"x":[0],"y":[0]}}],"ix":2}},{"ty":"st","c":{"a":0,"k":[0.1803921568627451,0.44313725490196076,0.6705882352941176],"ix":2},"o":{"a":0,"k":100,"ix":2},"w":{"a":0,"k":2,"ix":2},"hd":false,"lc":2,"lj":2},{"ty":"fl","c":{"a":0,"k":[0.4980392156862745,0.7686274509803922,1],"ix":2},"o":{"a":0,"k":100,"ix":2},"r":1,"bm":0,"nm":"Fill 1","mn":"ADBE Vector Graphic - Fill","hd":false},{"ty":"tm","s":{"a":0,"k":0,"ix":2},"e":{"a":0,"k":100,"ix":2},"o":{"a":0,"k":0,"ix":2},"m":1,"hd":false},{"ty":"tr","hd":false,"p":{"a":0,"k":[0,0],"ix":2},"a":{"a":0,"k":[0,0],"ix":2},"s":{"a":0,"k":[100,100],"ix":2},"r":{"a":0,"k":0,"ix":2},"o":{"a":0,"k":100,"ix":2},"sk":{"a":0,"k":0,"ix":2},"sa":{"a":0,"k":0,"ix":2}}]}],"ip":0,"op":400,"st":0,"bm":0},{"ddd":0,"ind":5,"ty":4,"nm":"Group 1","sr":1,"ks":{"o":{"a":0,"k":100,"ix":2},"r":{"a":0,"k":0,"ix":2},"p":{"a":0,"k":[0,0],"ix":2},"a":{"a":0,"k":[0,0],"ix":2},"s":{"a":0,"k":[100,100],"ix":2}},"ao":0,"hd":false,"parent":3,"shapes":[{"ty":"gr","hd":false,"it":[{"ty":"sh","hd":false,"d":1,"ks":{"a":1,"k":[{"t":2,"s":[{"c":false,"v":[[-131.253,-52.256],[-74.421,-52.146]],"i":[[0,0],[0,0]],"o":[[0,0],[0,0]]}],"i":{"x":[1],"y":[1]},"o":{"x":[0],"y":[0]}},{"t":202,"s":[{"c":false,"v":[[-131.253,-52.256],[-74.421,-52.146]],"i":[[0,0],[0,0]],"o":[[0,0],[0,0]]}],"i":{"x":[1],"y":[1]},"o":{"x":[0],"y":[0]}},{"t":395,"s":[{"c":false,"v":[[-131.253,-52.256],[-74.421,-52.146]],"i":[[0,0],[0,0]],"o":[[0,0],[0,0]]}],"i":{"x":[1],"y":[1]},"o":{"x":[0],"y":[0]}}],"ix":2}},{"ty":"st","c":{"a":0,"k":[0.592156862745098,0.8352941176470589,0.8274509803921568],"ix":2},"o":{"a":0,"k":100,"ix":2},"w":{"a":0,"k":0.75,"ix":2},"hd":false,"lc":2,"lj":2},{"ty":"tm","s":{"a":0,"k":0,"ix":2},"e":{"a":0,"k":100,"ix":2},"o":{"a":0,"k":0,"ix":2},"m":1,"hd":false},{"ty":"tr","hd":false,"p":{"a":0,"k":[0,0],"ix":2},"a":{"a":0,"k":[0,0],"ix":2},"s":{"a":0,"k":[100,100],"ix":2},"r":{"a":0,"k":0,"ix":2},"o":{"a":0,"k":100,"ix":2},"sk":{"a":0,"k":0,"ix":2},"sa":{"a":0,"k":0,"ix":2}}]}],"ip":0,"op":400,"st":0,"bm":0},{"ddd":0,"ind":6,"ty":4,"nm":"Group 2","sr":1,"ks":{"o":{"a":0,"k":100,"ix":2},"r":{"a":0,"k":0,"ix":2},"p":{"a":0,"k":[0,0],"ix":2},"a":{"a":0,"k":[0,0],"ix":2},"s":{"a":0,"k":[100,100],"ix":2}},"ao":0,"hd":false,"parent":3,"shapes":[{"ty":"gr","hd":false,"it":[{"ty":"sh","hd":false,"d":1,"ks":{"a":1,"k":[{"t":2,"s":[{"c":false,"v":[[-135.367,-65.696],[-127.644,-70.122],[-124.651,-69.981],[-75.448,-70.187],[-72.164,-68.125],[-71.124,-52.825],[-74.446,-48.52],[-84.337,-48.068],[-87.312,-48.032],[-131.198,-48.47],[-135.257,-55.273],[-135.367,-65.696]],"i":[[0,0],[-8.911,-0.624],[-0.999,0.004],[0,0],[-0.556,-1.289],[0.782,-8.733],[1.864,-0.6],[5.034,-0.074],[0.435,0.003],[0,0],[-0.658,8.229],[0,0]],"o":[[0,0],[0.997,0.07],[0,0],[1.404,-0.006],[0.94,2.177],[-0.175,1.951],[-1.91,0.615],[-0.435,0.006],[0,0],[0,0],[0,0],[0,0]]}],"i":{"x":[1],"y":[1]},"o":{"x":[0],"y":[0]}},{"t":202,"s":[{"c":false,"v":[[-135.367,-65.696],[-127.644,-70.122],[-124.651,-69.981],[-75.448,-70.187],[-72.164,-68.125],[-71.124,-52.825],[-74.446,-48.52],[-84.337,-48.068],[-87.312,-48.032],[-131.198,-48.47],[-135.257,-55.273],[-135.367,-65.696]],"i":[[0,0],[-8.911,-0.624],[-0.999,0.004],[0,0],[-0.556,-1.289],[0.782,-8.733],[1.864,-0.6],[5.034,-0.074],[0.435,0.003],[0,0],[-0.658,8.229],[0,0]],"o":[[0,0],[0.997,0.07],[0,0],[1.404,-0.006],[0.94,2.177],[-0.175,1.951],[-1.91,0.615],[-0.435,0.006],[0,0],[0,0],[0,0],[0,0]]}],"i":{"x":[1],"y":[1]},"o":{"x":[0],"y":[0]}},{"t":395,"s":[{"c":false,"v":[[-135.367,-65.696],[-127.644,-70.122],[-124.651,-69.981],[-75.448,-70.187],[-72.164,-68.125],[-71.124,-52.825],[-74.446,-48.52],[-84.337,-48.068],[-87.312,-48.032],[-131.198,-48.47],[-135.257,-55.273],[-135.367,-65.696]],"i":[[0,0],[-8.911,-0.624],[-0.999,0.004],[0,0],[-0.556,-1.289],[0.782,-8.733],[1.864,-0.6],[5.034,-0.074],[0.435,0.003],[0,0],[-0.658,8.229],[0,0]],"o":[[0,0],[0.997,0.07],[0,0],[1.404,-0.006],[0.94,2.177],[-0.175,1.951],[-1.91,0.615],[-0.435,0.006],[0,0],[0,0],[0,0],[0,0]]}],"i":{"x":[1],"y":[1]},"o":{"x":[0],"y":[0]}}],"ix":2}},{"ty":"fl","c":{"a":0,"k":[0.12941176470588237,0.14901960784313725,0.25098039215686274],"ix":2},"o":{"a":0,"k":100,"ix":2},"r":1,"bm":0,"nm":"Fill 1","mn":"ADBE Vector Graphic - Fill","hd":false},{"ty":"tm","s":{"a":0,"k":0,"ix":2},"e":{"a":0,"k":100,"ix":2},"o":{"a":0,"k":0,"ix":2},"m":1,"hd":false},{"ty":"tr","hd":false,"p":{"a":0,"k":[0,0],"ix":2},"a":{"a":0,"k":[0,0],"ix":2},"s":{"a":0,"k":[100,100],"ix":2},"r":{"a":0,"k":0,"ix":2},"o":{"a":0,"k":100,"ix":2},"sk":{"a":0,"k":0,"ix":2},"sa":{"a":0,"k":0,"ix":2}}]}],"ip":0,"op":400,"st":0,"bm":0},{"ddd":0,"ind":7,"ty":4,"nm":"Group 2","sr":1,"ks":{"o":{"a":0,"k":100,"ix":2},"r":{"a":0,"k":0,"ix":2},"p":{"a":0,"k":[0,0],"ix":2},"a":{"a":0,"k":[0,0],"ix":2},"s":{"a":0,"k":[100,100],"ix":2}},"ao":0,"hd":false,"parent":3,"shapes":[{"ty":"gr","hd":false,"it":[{"ty":"sh","hd":false,"d":1,"ks":{"a":1,"k":[{"t":2,"s":[{"c":false,"v":[[-279.984,-127.771],[-241.847,-69.946],[-241.065,-65.814],[-205.475,-16.214],[-165.401,-8.383],[-158.277,-5.088],[-120.501,2.327],[-103.901,-3.11],[-113.044,-3.169],[-145.659,7.004],[-143.367,7.301],[-83.73,1.222],[-84.007,-2.503],[-100.423,-9.522],[-92.359,-16.105],[-67.025,-17.462],[-60.904,-22.497],[-61.419,-36.676],[-66.521,-51.981],[-117.209,-51.817]],"i":[[0,0],[-11.957,-59.549],[-0.415,-1.333],[-27.429,-0.055],[-9.659,-4.899],[-2.466,-0.897],[-17.092,-0.777],[12.139,1.703],[3.045,-0.335],[-14.165,-4.344],[-0.774,-0.022],[-11.008,7.108],[1.538,0.693],[0.749,0],[-15.47,-0.329],[0,0],[-0.7,2.847],[1.415,6.275],[3.291,2.304],[0,0]],"o":[[0,0],[0.275,1.369],[2.566,8.237],[0,0],[2.34,1.187],[7.06,2.568],[22.313,1.014],[-3.033,-0.426],[-12.672,1.395],[0.74,0.227],[7.456,0.21],[1.417,-0.915],[-5.076,-2.287],[-0.987,0],[0,0],[2.927,-0.157],[0.655,-2.662],[0,0],[0,0],[0,0]]}],"i":{"x":[1],"y":[1]},"o":{"x":[0],"y":[0]}},{"t":202,"s":[{"c":false,"v":[[-278.97,-110.658],[-241.847,-69.946],[-241.065,-65.814],[-204.1,-17.051],[-162.049,-8.676],[-154.925,-5.381],[-117.09,1.373],[-100.78,-4.878],[-109.914,-4.486],[-144.878,7.652],[-142.586,7.949],[-83.97,1.243],[-84.247,-2.482],[-99.465,-9.606],[-91.401,-16.188],[-63.672,-17.755],[-57.551,-22.79],[-61.419,-36.676],[-66.521,-51.981],[-117.209,-51.817]],"i":[[0,0],[-9.306,-47.982],[-0.415,-1.333],[-27.429,-0.055],[-9.659,-4.899],[-2.466,-0.897],[-17.11,0.068],[12.209,1.102],[3.024,-0.485],[-14.165,-4.344],[-0.774,-0.022],[-11.008,7.108],[1.538,0.693],[0.749,0],[-15.47,-0.329],[0,0],[-0.7,2.847],[1.415,6.275],[3.291,2.304],[0,0]],"o":[[0,0],[0.266,1.371],[2.566,8.237],[0,0],[2.34,1.187],[7.06,2.568],[22.335,-0.089],[-3.051,-0.275],[-12.587,2.019],[0.74,0.227],[7.456,0.21],[1.417,-0.915],[-5.076,-2.287],[-0.987,0],[0,0],[2.927,-0.157],[0.655,-2.662],[0,0],[0,0],[0,0]]}],"i":{"x":[1],"y":[1]},"o":{"x":[0],"y":[0]}},{"t":395,"s":[{"c":false,"v":[[-279.984,-127.771],[-241.847,-69.946],[-241.065,-65.814],[-205.475,-16.214],[-165.401,-8.383],[-158.277,-5.088],[-120.501,2.327],[-103.901,-3.11],[-113.044,-3.169],[-145.659,7.004],[-143.367,7.301],[-83.73,1.222],[-84.007,-2.503],[-100.423,-9.522],[-92.359,-16.105],[-67.025,-17.462],[-60.904,-22.497],[-61.419,-36.676],[-66.521,-51.981],[-117.209,-51.817]],"i":[[0,0],[-11.957,-59.549],[-0.415,-1.333],[-27.429,-0.055],[-9.659,-4.899],[-2.466,-0.897],[-17.092,-0.777],[12.139,1.703],[3.045,-0.335],[-14.165,-4.344],[-0.774,-0.022],[-11.008,7.108],[1.538,0.693],[0.749,0],[-15.47,-0.329],[0,0],[-0.7,2.847],[1.415,6.275],[3.291,2.304],[0,0]],"o":[[0,0],[0.275,1.369],[2.566,8.237],[0,0],[2.34,1.187],[7.06,2.568],[22.313,1.014],[-3.033,-0.426],[-12.672,1.395],[0.74,0.227],[7.456,0.21],[1.417,-0.915],[-5.076,-2.287],[-0.987,0],[0,0],[2.927,-0.157],[0.655,-2.662],[0,0],[0,0],[0,0]]}],"i":{"x":[1],"y":[1]},"o":{"x":[0],"y":[0]}}],"ix":2}},{"ty":"st","c":{"a":0,"k":[0.12941176470588237,0.14901960784313725,0.25098039215686274],"ix":2},"o":{"a":0,"k":100,"ix":2},"w":{"a":0,"k":1,"ix":2},"hd":false,"lc":2,"lj":2},{"ty":"tm","s":{"a":0,"k":0,"ix":2},"e":{"a":0,"k":100,"ix":2},"o":{"a":0,"k":0,"ix":2},"m":1,"hd":false},{"ty":"tr","hd":false,"p":{"a":0,"k":[0,0],"ix":2},"a":{"a":0,"k":[0,0],"ix":2},"s":{"a":0,"k":[100,100],"ix":2},"r":{"a":0,"k":0,"ix":2},"o":{"a":0,"k":100,"ix":2},"sk":{"a":0,"k":0,"ix":2},"sa":{"a":0,"k":0,"ix":2}}]}],"ip":0,"op":400,"st":0,"bm":0},{"ddd":0,"ind":8,"ty":3,"nm":"","sr":1,"ks":{"o":{"a":0,"k":100,"ix":2},"r":{"a":1,"k":[{"t":2,"s":[0],"i":{"x":[1],"y":[1]},"o":{"x":[0],"y":[0]}},{"t":202,"s":[3],"i":{"x":[1],"y":[1]},"o":{"x":[0],"y":[0]}},{"t":396,"s":[0],"i":{"x":[1],"y":[1]},"o":{"x":[0],"y":[0]}}],"ix":2},"p":{"a":0,"k":[-246.911,-135.509],"ix":2},"a":{"a":0,"k":[-246.911,-135.509],"ix":2},"s":{"a":0,"k":[100,100],"ix":2}},"ao":0,"ip":0,"op":400,"st":0,"bm":0,"hd":false,"parent":2},{"ddd":0,"ind":9,"ty":4,"nm":"Group 1","sr":1,"ks":{"o":{"a":0,"k":100,"ix":2},"r":{"a":0,"k":0,"ix":2},"p":{"a":0,"k":[0,0],"ix":2},"a":{"a":0,"k":[0,0],"ix":2},"s":{"a":0,"k":[100,100],"ix":2}},"ao":0,"hd":false,"parent":8,"shapes":[{"ty":"gr","hd":false,"it":[{"ty":"sh","hd":false,"d":1,"ks":{"a":0,"k":{"c":false,"v":[[-256.747,-182.897],[-259.75,-183.247],[-260.294,-184.138],[-259.373,-184.664],[-253.788,-185.102],[-252.717,-186.869],[-254.181,-189.395],[-254.286,-190.417],[-253.23,-190.519],[-251.222,-186.869],[-252.852,-183.977],[-256.747,-182.897]],"i":[[1.329,0],[0.105,0.029],[-0.105,0.394],[-0.407,-0.102],[-1.449,1.124],[0,0.642],[0.015,0.015],[-0.257,0.307],[-0.317,-0.248],[0.015,-2.015],[1.071,-0.832],[1.329,0]],"o":[[-1.569,0],[-0.408,-0.102],[0.106,-0.394],[1.057,0.263],[0.709,-0.555],[0.015,-1.314],[-0.317,-0.263],[0.271,-0.307],[0.076,0.073],[-0.016,1.081],[-1.057,0.847],[-1.569,0]]}}},{"ty":"fl","c":{"a":0,"k":[0.12941176470588237,0.14901960784313725,0.25098039215686274],"ix":2},"o":{"a":0,"k":100,"ix":2},"r":1,"bm":0,"nm":"Fill 1","mn":"ADBE Vector Graphic - Fill","hd":false},{"ty":"tm","s":{"a":0,"k":0,"ix":2},"e":{"a":0,"k":100,"ix":2},"o":{"a":0,"k":0,"ix":2},"m":1,"hd":false},{"ty":"tr","hd":false,"p":{"a":0,"k":[0,0],"ix":2},"a":{"a":0,"k":[0,0],"ix":2},"s":{"a":0,"k":[100,100],"ix":2},"r":{"a":0,"k":0,"ix":2},"o":{"a":0,"k":100,"ix":2},"sk":{"a":0,"k":0,"ix":2},"sa":{"a":0,"k":0,"ix":2}}]}],"ip":0,"op":400,"st":0,"bm":0},{"ddd":0,"ind":10,"ty":4,"nm":"Group 2","sr":1,"ks":{"o":{"a":0,"k":100,"ix":2},"r":{"a":0,"k":0,"ix":2},"p":{"a":0,"k":[0,0],"ix":2},"a":{"a":0,"k":[0,0],"ix":2},"s":{"a":0,"k":[100,100],"ix":2}},"ao":0,"hd":false,"parent":8,"shapes":[{"ty":"gr","hd":false,"it":[{"ty":"sh","hd":false,"d":1,"ks":{"a":0,"k":{"c":false,"v":[[-253.349,-172.951],[-256.262,-173.404],[-256.715,-174.338],[-255.749,-174.776],[-250.044,-175.273],[-248.7,-177.01],[-250.21,-180.792],[-250.134,-181.829],[-249.078,-181.756],[-247.206,-176.791],[-249.244,-174.032],[-253.349,-172.951]],"i":[[1.222,0],[0.09,0.029],[-0.136,0.38],[-0.392,-0.131],[-2.626,1.548],[-0.121,0.701],[0.015,0.015],[-0.317,0.278],[-0.271,-0.307],[0.377,-2.424],[1.163,-0.701],[1.222,0]],"o":[[-1.615,0],[-0.393,-0.146],[0.151,-0.38],[0.03,0.015],[0.785,-0.467],[0.287,-1.752],[-0.271,-0.307],[0.317,-0.263],[0.091,0.102],[-0.181,1.139],[-1.403,0.832],[-1.615,0]]}}},{"ty":"fl","c":{"a":0,"k":[0.12941176470588237,0.14901960784313725,0.25098039215686274],"ix":2},"o":{"a":0,"k":100,"ix":2},"r":1,"bm":0,"nm":"Fill 1","mn":"ADBE Vector Graphic - Fill","hd":false},{"ty":"tm","s":{"a":0,"k":0,"ix":2},"e":{"a":0,"k":100,"ix":2},"o":{"a":0,"k":0,"ix":2},"m":1,"hd":false},{"ty":"tr","hd":false,"p":{"a":0,"k":[0,0],"ix":2},"a":{"a":0,"k":[0,0],"ix":2},"s":{"a":0,"k":[100,100],"ix":2},"r":{"a":0,"k":0,"ix":2},"o":{"a":0,"k":100,"ix":2},"sk":{"a":0,"k":0,"ix":2},"sa":{"a":0,"k":0,"ix":2}}]}],"ip":0,"op":400,"st":0,"bm":0},{"ddd":0,"ind":11,"ty":4,"nm":"Group 3","sr":1,"ks":{"o":{"a":0,"k":100,"ix":2},"r":{"a":0,"k":0,"ix":2},"p":{"a":0,"k":[0,0],"ix":2},"a":{"a":0,"k":[0,0],"ix":2},"s":{"a":0,"k":[100,100],"ix":2}},"ao":0,"hd":false,"parent":8,"shapes":[{"ty":"gr","hd":false,"it":[{"ty":"sh","hd":false,"d":1,"ks":{"a":0,"k":{"c":false,"v":[[-269.831,-171.855],[-272.744,-172.308],[-273.197,-173.243],[-272.231,-173.681],[-266.526,-174.177],[-265.183,-175.915],[-266.692,-179.697],[-266.617,-180.733],[-265.56,-180.66],[-263.688,-175.696],[-265.726,-172.936],[-269.831,-171.855]],"i":[[1.237,0],[0.09,0.029],[-0.136,0.38],[-0.378,-0.131],[-2.626,1.548],[-0.12,0.701],[0.015,0.015],[-0.317,0.277],[-0.272,-0.307],[0.377,-2.424],[1.162,-0.701],[1.237,0]],"o":[[-1.615,0],[-0.393,-0.146],[0.151,-0.38],[0.03,0.015],[0.785,-0.467],[0.287,-1.752],[-0.272,-0.307],[0.317,-0.263],[0.091,0.102],[-0.182,1.139],[-1.404,0.847],[-1.615,0]]}}},{"ty":"fl","c":{"a":0,"k":[0.12941176470588237,0.14901960784313725,0.25098039215686274],"ix":2},"o":{"a":0,"k":100,"ix":2},"r":1,"bm":0,"nm":"Fill 1","mn":"ADBE Vector Graphic - Fill","hd":false},{"ty":"tm","s":{"a":0,"k":0,"ix":2},"e":{"a":0,"k":100,"ix":2},"o":{"a":0,"k":0,"ix":2},"m":1,"hd":false},{"ty":"tr","hd":false,"p":{"a":0,"k":[0,0],"ix":2},"a":{"a":0,"k":[0,0],"ix":2},"s":{"a":0,"k":[100,100],"ix":2},"r":{"a":0,"k":0,"ix":2},"o":{"a":0,"k":100,"ix":2},"sk":{"a":0,"k":0,"ix":2},"sa":{"a":0,"k":0,"ix":2}}]}],"ip":0,"op":400,"st":0,"bm":0},{"ddd":0,"ind":12,"ty":4,"nm":"Group 1","sr":1,"ks":{"o":{"a":0,"k":100,"ix":2},"r":{"a":0,"k":0,"ix":2},"p":{"a":0,"k":[0,0],"ix":2},"a":{"a":0,"k":[0,0],"ix":2},"s":{"a":0,"k":[100,100],"ix":2}},"ao":0,"hd":false,"parent":8,"shapes":[{"ty":"gr","hd":false,"it":[{"ty":"sh","hd":false,"d":1,"ks":{"a":0,"k":{"c":false,"v":[[-285.676,-128.428],[-284.513,-141.38],[-310.686,-150.039]],"i":[[0,0],[3.305,9.52],[7.728,-12.295]],"o":[[0,0],[-2.793,-8.031],[0,0]]}}},{"ty":"st","c":{"a":0,"k":[0.592156862745098,0.8392156862745098,0.8313725490196079],"ix":2},"o":{"a":0,"k":100,"ix":2},"w":{"a":0,"k":1,"ix":2},"hd":false,"lc":2,"lj":2},{"ty":"tm","s":{"a":0,"k":0,"ix":2},"e":{"a":0,"k":100,"ix":2},"o":{"a":0,"k":0,"ix":2},"m":1,"hd":false},{"ty":"tr","hd":false,"p":{"a":0,"k":[0,0],"ix":2},"a":{"a":0,"k":[0,0],"ix":2},"s":{"a":0,"k":[100,100],"ix":2},"r":{"a":0,"k":0,"ix":2},"o":{"a":0,"k":100,"ix":2},"sk":{"a":0,"k":0,"ix":2},"sa":{"a":0,"k":0,"ix":2}}]}],"ip":0,"op":400,"st":0,"bm":0},{"ddd":0,"ind":13,"ty":4,"nm":"Group 2","sr":1,"ks":{"o":{"a":0,"k":100,"ix":2},"r":{"a":0,"k":0,"ix":2},"p":{"a":0,"k":[0,0],"ix":2},"a":{"a":0,"k":[0,0],"ix":2},"s":{"a":0,"k":[100,100],"ix":2}},"ao":0,"hd":false,"parent":8,"shapes":[{"ty":"gr","hd":false,"it":[{"ty":"sh","hd":false,"d":1,"ks":{"a":0,"k":{"c":false,"v":[[-282.976,-119.479],[-272.184,-150.698],[-308.801,-152.844],[-282.976,-119.479]],"i":[[-29.191,7.637],[8.301,12.222],[9.554,-11.682],[-29.191,7.637]],"o":[[15.154,-3.972],[-9.449,-13.886],[-10.686,13.068],[15.154,-3.972]]}}},{"ty":"fl","c":{"a":0,"k":[0.12941176470588237,0.14901960784313725,0.25098039215686274],"ix":2},"o":{"a":0,"k":100,"ix":2},"r":1,"bm":0,"nm":"Fill 1","mn":"ADBE Vector Graphic - Fill","hd":false},{"ty":"tm","s":{"a":0,"k":0,"ix":2},"e":{"a":0,"k":100,"ix":2},"o":{"a":0,"k":0,"ix":2},"m":1,"hd":false},{"ty":"tr","hd":false,"p":{"a":0,"k":[0,0],"ix":2},"a":{"a":0,"k":[0,0],"ix":2},"s":{"a":0,"k":[100,100],"ix":2},"r":{"a":0,"k":0,"ix":2},"o":{"a":0,"k":100,"ix":2},"sk":{"a":0,"k":0,"ix":2},"sa":{"a":0,"k":0,"ix":2}}]}],"ip":0,"op":400,"st":0,"bm":0},{"ddd":0,"ind":14,"ty":4,"nm":"Group 5","sr":1,"ks":{"o":{"a":0,"k":100,"ix":2},"r":{"a":0,"k":0,"ix":2},"p":{"a":0,"k":[0,0],"ix":2},"a":{"a":0,"k":[0,0],"ix":2},"s":{"a":0,"k":[100,100],"ix":2}},"ao":0,"hd":false,"parent":8,"shapes":[{"ty":"gr","hd":false,"it":[{"ty":"sh","hd":false,"d":1,"ks":{"a":0,"k":{"c":false,"v":[[-289.981,-157.635],[-302.569,-186.459],[-277.408,-203.222],[-285.966,-203.82],[-315.157,-179.494],[-299.747,-151.721],[-289.981,-157.635]],"i":[[5.524,5.739],[-6.43,7.943],[0,0],[6.943,-2.424],[-0.196,-9.696],[-5.81,-5.914],[5.524,5.739]],"o":[[0,0],[6.43,-7.958],[0,0],[-6.943,2.424],[0.196,9.696],[5.6,5.666],[0,0]]}}},{"ty":"fl","c":{"a":0,"k":[0.12941176470588237,0.14901960784313725,0.25098039215686274],"ix":2},"o":{"a":0,"k":100,"ix":2},"r":1,"bm":0,"nm":"Fill 1","mn":"ADBE Vector Graphic - Fill","hd":false},{"ty":"tm","s":{"a":0,"k":0,"ix":2},"e":{"a":0,"k":100,"ix":2},"o":{"a":0,"k":0,"ix":2},"m":1,"hd":false},{"ty":"tr","hd":false,"p":{"a":0,"k":[0,0],"ix":2},"a":{"a":0,"k":[0,0],"ix":2},"s":{"a":0,"k":[100,100],"ix":2},"r":{"a":0,"k":0,"ix":2},"o":{"a":0,"k":100,"ix":2},"sk":{"a":0,"k":0,"ix":2},"sa":{"a":0,"k":0,"ix":2}}]}],"ip":0,"op":400,"st":0,"bm":0},{"ddd":0,"ind":15,"ty":4,"nm":"Group 6","sr":1,"ks":{"o":{"a":0,"k":100,"ix":2},"r":{"a":0,"k":0,"ix":2},"p":{"a":0,"k":[0,0],"ix":2},"a":{"a":0,"k":[0,0],"ix":2},"s":{"a":0,"k":[100,100],"ix":2}},"ao":0,"hd":false,"parent":8,"shapes":[{"ty":"gr","hd":false,"it":[{"ty":"sh","hd":false,"d":1,"ks":{"a":0,"k":{"c":false,"v":[[-251.959,-192.68],[-284.078,-201.879],[-319.79,-166.09],[-268.155,-138.011],[-228.338,-183.247],[-251.959,-192.68]],"i":[[6.173,-0.248],[15.938,-5.958],[-2.565,-15.405],[-26.278,12.295],[5.403,11.682],[6.173,-0.248]],"o":[[-6.989,0.278],[-15.924,5.972],[2.566,15.405],[30.836,-14.412],[-5.887,-12.777],[-6.989,0.278]]}}},{"ty":"fl","c":{"a":0,"k":[0.5019607843137255,0.7725490196078432,1],"ix":2},"o":{"a":0,"k":100,"ix":2},"r":1,"bm":0,"nm":"Fill 1","mn":"ADBE Vector Graphic - Fill","hd":false},{"ty":"tm","s":{"a":0,"k":0,"ix":2},"e":{"a":0,"k":100,"ix":2},"o":{"a":0,"k":0,"ix":2},"m":1,"hd":false},{"ty":"tr","hd":false,"p":{"a":0,"k":[0,0],"ix":2},"a":{"a":0,"k":[0,0],"ix":2},"s":{"a":0,"k":[100,100],"ix":2},"r":{"a":0,"k":0,"ix":2},"o":{"a":0,"k":100,"ix":2},"sk":{"a":0,"k":0,"ix":2},"sa":{"a":0,"k":0,"ix":2}}]}],"ip":0,"op":400,"st":0,"bm":0},{"ddd":0,"ind":16,"ty":4,"nm":"Group 7","sr":1,"ks":{"o":{"a":0,"k":100,"ix":2},"r":{"a":0,"k":0,"ix":2},"p":{"a":0,"k":[0,0],"ix":2},"a":{"a":0,"k":[0,0],"ix":2},"s":{"a":0,"k":[100,100],"ix":2}},"ao":0,"hd":false,"parent":8,"shapes":[{"ty":"gr","hd":false,"it":[{"ty":"sh","hd":false,"d":1,"ks":{"a":0,"k":{"c":false,"v":[[-235.039,-157.178],[-224.247,-188.397],[-260.863,-190.544],[-235.039,-157.178]],"i":[[-29.19,7.637],[8.302,12.222],[9.554,-11.681],[-29.19,7.637]],"o":[[15.154,-3.972],[-9.448,-13.886],[-10.687,13.069],[15.154,-3.972]]}}},{"ty":"fl","c":{"a":0,"k":[0.12941176470588237,0.14901960784313725,0.25098039215686274],"ix":2},"o":{"a":0,"k":100,"ix":2},"r":1,"bm":0,"nm":"Fill 1","mn":"ADBE Vector Graphic - Fill","hd":false},{"ty":"tm","s":{"a":0,"k":0,"ix":2},"e":{"a":0,"k":100,"ix":2},"o":{"a":0,"k":0,"ix":2},"m":1,"hd":false},{"ty":"tr","hd":false,"p":{"a":0,"k":[0,0],"ix":2},"a":{"a":0,"k":[0,0],"ix":2},"s":{"a":0,"k":[100,100],"ix":2},"r":{"a":0,"k":0,"ix":2},"o":{"a":0,"k":100,"ix":2},"sk":{"a":0,"k":0,"ix":2},"sa":{"a":0,"k":0,"ix":2}}]}],"ip":0,"op":400,"st":0,"bm":0},{"ddd":0,"ind":17,"ty":3,"nm":"","sr":1,"ks":{"o":{"a":0,"k":100,"ix":2},"r":{"a":1,"k":[{"t":2,"s":[6],"i":{"x":[1],"y":[1]},"o":{"x":[0],"y":[0]}},{"t":202,"s":[-9],"i":{"x":[1],"y":[1]},"o":{"x":[0],"y":[0]}},{"t":396,"s":[6],"i":{"x":[1],"y":[1]},"o":{"x":[0],"y":[0]}}],"ix":2},"p":{"a":0,"k":[-264.883,-87.333],"ix":2},"a":{"a":0,"k":[-264.883,-87.333],"ix":2},"s":{"a":0,"k":[100,100],"ix":2}},"ao":0,"ip":0,"op":400,"st":0,"bm":0,"hd":false,"parent":2},{"ddd":0,"ind":18,"ty":4,"nm":"Group 1","sr":1,"ks":{"o":{"a":0,"k":100,"ix":2},"r":{"a":0,"k":0,"ix":2},"p":{"a":0,"k":[0,0],"ix":2},"a":{"a":0,"k":[0,0],"ix":2},"s":{"a":0,"k":[100,100],"ix":2}},"ao":0,"hd":false,"parent":17,"shapes":[{"ty":"gr","hd":false,"it":[{"ty":"sh","hd":false,"d":1,"ks":{"a":1,"k":[{"t":2,"s":[{"c":false,"v":[[-265.304,252.348],[-252.157,229.289]],"i":[[0,0],[-4.045,20.631]],"o":[[0,0],[0,0]]}],"i":{"x":[1],"y":[1]},"o":{"x":[0],"y":[0]}},{"t":202,"s":[{"c":false,"v":[[-242.208,253.569],[-236.622,227.62]],"i":[[0,0],[2.361,20.891]],"o":[[0,0],[0,0]]}],"i":{"x":[1],"y":[1]},"o":{"x":[0],"y":[0]}},{"t":396,"s":[{"c":false,"v":[[-265.304,252.348],[-252.157,229.289]],"i":[[0,0],[-4.045,20.631]],"o":[[0,0],[0,0]]}],"i":{"x":[1],"y":[1]},"o":{"x":[0],"y":[0]}}],"ix":2}},{"ty":"st","c":{"a":0,"k":[0.1803921568627451,0.44313725490196076,0.6705882352941176],"ix":2},"o":{"a":0,"k":100,"ix":2},"w":{"a":0,"k":2,"ix":2},"hd":false,"lc":2,"lj":2},{"ty":"tm","s":{"a":0,"k":0,"ix":2},"e":{"a":0,"k":100,"ix":2},"o":{"a":0,"k":0,"ix":2},"m":1,"hd":false},{"ty":"tr","hd":false,"p":{"a":0,"k":[0,0],"ix":2},"a":{"a":0,"k":[0,0],"ix":2},"s":{"a":0,"k":[100,100],"ix":2},"r":{"a":0,"k":0,"ix":2},"o":{"a":0,"k":100,"ix":2},"sk":{"a":0,"k":0,"ix":2},"sa":{"a":0,"k":0,"ix":2}}]}],"ip":0,"op":400,"st":0,"bm":0},{"ddd":0,"ind":19,"ty":4,"nm":"Group 2","sr":1,"ks":{"o":{"a":0,"k":100,"ix":2},"r":{"a":0,"k":0,"ix":2},"p":{"a":0,"k":[0,0],"ix":2},"a":{"a":0,"k":[0,0],"ix":2},"s":{"a":0,"k":[100,100],"ix":2}},"ao":0,"hd":false,"parent":17,"shapes":[{"ty":"gr","hd":false,"it":[{"ty":"sh","hd":false,"d":1,"ks":{"a":1,"k":[{"t":2,"s":[{"c":false,"v":[[-239.414,234.346],[-237.189,224.84]],"i":[[0,0],[-2.225,3.641]],"o":[[0,0],[0,0]]}],"i":{"x":[1],"y":[1]},"o":{"x":[0],"y":[0]}},{"t":202,"s":[{"c":false,"v":[[-222.948,228.601],[-223.692,218.866]],"i":[[0,0],[-1.024,4.142]],"o":[[0,0],[0,0]]}],"i":{"x":[1],"y":[1]},"o":{"x":[0],"y":[0]}},{"t":396,"s":[{"c":false,"v":[[-239.414,234.346],[-237.189,224.84]],"i":[[0,0],[-2.225,3.641]],"o":[[0,0],[0,0]]}],"i":{"x":[1],"y":[1]},"o":{"x":[0],"y":[0]}}],"ix":2}},{"ty":"st","c":{"a":0,"k":[0.1803921568627451,0.44313725490196076,0.6705882352941176],"ix":2},"o":{"a":0,"k":100,"ix":2},"w":{"a":0,"k":2,"ix":2},"hd":false,"lc":2,"lj":2},{"ty":"tm","s":{"a":0,"k":0,"ix":2},"e":{"a":0,"k":100,"ix":2},"o":{"a":0,"k":0,"ix":2},"m":1,"hd":false},{"ty":"tr","hd":false,"p":{"a":0,"k":[0,0],"ix":2},"a":{"a":0,"k":[0,0],"ix":2},"s":{"a":0,"k":[100,100],"ix":2},"r":{"a":0,"k":0,"ix":2},"o":{"a":0,"k":100,"ix":2},"sk":{"a":0,"k":0,"ix":2},"sa":{"a":0,"k":0,"ix":2}}]}],"ip":0,"op":400,"st":0,"bm":0},{"ddd":0,"ind":20,"ty":4,"nm":"Group 3","sr":1,"ks":{"o":{"a":0,"k":100,"ix":2},"r":{"a":0,"k":0,"ix":2},"p":{"a":0,"k":[0,0],"ix":2},"a":{"a":0,"k":[0,0],"ix":2},"s":{"a":0,"k":[100,100],"ix":2}},"ao":0,"hd":false,"parent":17,"shapes":[{"ty":"gr","hd":false,"it":[{"ty":"sh","hd":false,"d":1,"ks":{"a":1,"k":[{"t":2,"s":[{"c":false,"v":[[-289.044,-125.405],[-230.872,-48.73],[-230.873,51.423],[-231.526,156.474],[-221.706,237.06],[-220.983,241.76],[-231.548,247.494],[-235.39,245.081],[-237.998,232.526],[-257.503,262.058],[-265.086,257.542],[-262.27,249.92],[-272.234,252.645],[-272.832,248.868],[-267.327,219.834],[-289.504,134.232],[-310.252,-28.025],[-289.044,-125.405]],"i":[[0,0],[-10.518,-42.88],[-1.95,-47.88],[2.925,-23.215],[-14.13,-32.002],[0.252,-1.598],[7.996,0.982],[0.852,1.333],[-1.666,4.719],[9.571,-4.697],[0.252,3.721],[-2.531,2.32],[4.351,3.276],[-0.757,1.232],[2.865,13.491],[11.012,48.18],[-1.483,43.646],[0,0]],"o":[[0,0],[0,0],[1.607,39.471],[0,0],[0.653,1.48],[-0.463,2.937],[-1.571,-0.193],[-1.749,-2.736],[0,0],[-3.348,1.643],[-0.157,-2.321],[0,0],[-1.155,-0.87],[2.592,-4.214],[0,0],[-12.085,-52.874],[2.471,-72.702],[0,0]]}],"i":{"x":[1],"y":[1]},"o":{"x":[0],"y":[0]}},{"t":202,"s":[{"c":false,"v":[[-286.175,-125.707],[-236.16,-40.076],[-230.873,51.423],[-224.346,151.491],[-205.245,225.851],[-203.14,230.115],[-211.485,238.767],[-215.875,237.624],[-222.147,226.438],[-231.843,260.476],[-240.434,258.456],[-240.047,250.34],[-248.726,255.941],[-250.435,252.52],[-253.937,223.177],[-284.612,136.519],[-310.252,-28.025],[-286.175,-125.707]],"i":[[0,0],[-10.518,-42.88],[-1.95,-47.88],[0.059,-23.398],[-23.12,-26.254],[-0.242,-1.6],[7.92,-1.473],[1.214,1.014],[-0.166,5.002],[7.71,-7.363],[1.362,3.472],[-1.714,2.975],[5.136,1.813],[-0.351,1.402],[6.798,12],[16.831,46.469],[-0.572,43.668],[0,0]],"o":[[0,0],[0,0],[1.607,39.471],[0,0],[1.069,1.214],[0.444,2.94],[-1.556,0.289],[-2.492,-2.082],[0,0],[-2.697,2.576],[-0.849,-2.166],[0,0],[-1.363,-0.481],[1.201,-4.8],[0,0],[-18.471,-50.996],[0.984,-75.116],[0,0]]}],"i":{"x":[1],"y":[1]},"o":{"x":[0],"y":[0]}},{"t":396,"s":[{"c":false,"v":[[-289.044,-125.405],[-230.872,-48.73],[-230.873,51.423],[-231.526,156.474],[-221.706,237.06],[-220.983,241.76],[-231.548,247.494],[-235.39,245.081],[-237.998,232.526],[-257.503,262.058],[-265.086,257.542],[-262.27,249.92],[-272.234,252.645],[-272.832,248.868],[-267.327,219.834],[-289.504,134.232],[-310.252,-28.025],[-289.044,-125.405]],"i":[[0,0],[-10.518,-42.88],[-1.95,-47.88],[2.925,-23.215],[-14.13,-32.002],[0.252,-1.598],[7.996,0.982],[0.852,1.333],[-1.666,4.719],[9.571,-4.697],[0.252,3.721],[-2.531,2.32],[4.351,3.276],[-0.757,1.232],[2.865,13.491],[11.012,48.18],[-1.483,43.646],[0,0]],"o":[[0,0],[0,0],[1.607,39.471],[0,0],[0.653,1.48],[-0.463,2.937],[-1.571,-0.193],[-1.749,-2.736],[0,0],[-3.348,1.643],[-0.157,-2.321],[0,0],[-1.155,-0.87],[2.592,-4.214],[0,0],[-12.085,-52.874],[2.471,-72.702],[0,0]]}],"i":{"x":[1],"y":[1]},"o":{"x":[0],"y":[0]}}],"ix":2}},{"ty":"fl","c":{"a":0,"k":[0.4980392156862745,0.7686274509803922,1],"ix":2},"o":{"a":0,"k":100,"ix":2},"r":1,"bm":0,"nm":"Fill 1","mn":"ADBE Vector Graphic - Fill","hd":false},{"ty":"tm","s":{"a":0,"k":0,"ix":2},"e":{"a":0,"k":100,"ix":2},"o":{"a":0,"k":0,"ix":2},"m":1,"hd":false},{"ty":"tr","hd":false,"p":{"a":0,"k":[0,0],"ix":2},"a":{"a":0,"k":[0,0],"ix":2},"s":{"a":0,"k":[100,100],"ix":2},"r":{"a":0,"k":0,"ix":2},"o":{"a":0,"k":100,"ix":2},"sk":{"a":0,"k":0,"ix":2},"sa":{"a":0,"k":0,"ix":2}}]}],"ip":0,"op":400,"st":0,"bm":0},{"ddd":0,"ind":21,"ty":4,"nm":"Group 1","sr":1,"ks":{"o":{"a":0,"k":100,"ix":2},"r":{"a":0,"k":0,"ix":2},"p":{"a":0,"k":[0,0],"ix":2},"a":{"a":0,"k":[0,0],"ix":2},"s":{"a":0,"k":[100,100],"ix":2}},"ao":0,"hd":false,"parent":2,"shapes":[{"ty":"gr","hd":false,"it":[{"ty":"sh","hd":false,"d":1,"ks":{"a":0,"k":{"c":false,"v":[[-196.533,-138.875],[-135.806,-94.441],[-105.525,-128.014]],"i":[[0,0],[-33.902,-9.71],[0,0]],"o":[[0,0],[0,0],[0,0]]}}},{"ty":"st","c":{"a":0,"k":[0.1803921568627451,0.44313725490196076,0.6705882352941176],"ix":2},"o":{"a":0,"k":100,"ix":2},"w":{"a":0,"k":2,"ix":2},"hd":false,"lc":2,"lj":2},{"ty":"tm","s":{"a":0,"k":0,"ix":2},"e":{"a":0,"k":100,"ix":2},"o":{"a":0,"k":0,"ix":2},"m":1,"hd":false},{"ty":"tr","hd":false,"p":{"a":0,"k":[0,0],"ix":2},"a":{"a":0,"k":[0,0],"ix":2},"s":{"a":0,"k":[100,100],"ix":2},"r":{"a":0,"k":0,"ix":2},"o":{"a":0,"k":100,"ix":2},"sk":{"a":0,"k":0,"ix":2},"sa":{"a":0,"k":0,"ix":2}}]}],"ip":0,"op":400,"st":0,"bm":0},{"ddd":0,"ind":22,"ty":4,"nm":"Group 2","sr":1,"ks":{"o":{"a":0,"k":100,"ix":2},"r":{"a":0,"k":0,"ix":2},"p":{"a":0,"k":[0,0],"ix":2},"a":{"a":0,"k":[0,0],"ix":2},"s":{"a":0,"k":[100,100],"ix":2}},"ao":0,"hd":false,"parent":2,"shapes":[{"ty":"gr","hd":false,"it":[{"ty":"sh","hd":false,"d":1,"ks":{"a":0,"k":{"c":false,"v":[[-70.842,-77.365],[-71.597,-78.022],[-70.918,-78.825],[-8.159,-83.06],[-7.374,-82.374],[-8.084,-81.614],[-70.752,-77.38],[-70.842,-77.365]],"i":[[0.03,0],[0.045,0.379],[-0.423,0.043],[-35.938,1.679],[-0.015,-0.394],[0.408,-0.015],[0.257,-0.029],[0.03,0]],"o":[[-0.378,0],[-0.045,-0.409],[0.257,-0.03],[0.468,-0.058],[0.015,0.409],[-35.892,1.679],[-0.045,0.015],[-0.378,0]]}}},{"ty":"fl","c":{"a":0,"k":[0.17647058823529413,0.4470588235294118,0.6745098039215687],"ix":2},"o":{"a":0,"k":100,"ix":2},"r":1,"bm":0,"nm":"Fill 1","mn":"ADBE Vector Graphic - Fill","hd":false},{"ty":"tm","s":{"a":0,"k":0,"ix":2},"e":{"a":0,"k":100,"ix":2},"o":{"a":0,"k":0,"ix":2},"m":1,"hd":false},{"ty":"tr","hd":false,"p":{"a":0,"k":[0,0],"ix":2},"a":{"a":0,"k":[0,0],"ix":2},"s":{"a":0,"k":[100,100],"ix":2},"r":{"a":0,"k":0,"ix":2},"o":{"a":0,"k":100,"ix":2},"sk":{"a":0,"k":0,"ix":2},"sa":{"a":0,"k":0,"ix":2}}]}],"ip":0,"op":400,"st":0,"bm":0},{"ddd":0,"ind":23,"ty":4,"nm":"Group 1","sr":1,"ks":{"o":{"a":0,"k":100,"ix":2},"r":{"a":0,"k":0,"ix":2},"p":{"a":0,"k":[0,0],"ix":2},"a":{"a":0,"k":[0,0],"ix":2},"s":{"a":0,"k":[100,100],"ix":2}},"ao":0,"hd":false,"parent":2,"shapes":[{"ty":"gr","hd":false,"it":[{"ty":"sh","hd":false,"d":1,"ks":{"a":0,"k":{"c":false,"v":[[133.797,-78.858],[133.691,-78.858],[56.458,-83.122],[55.809,-83.122],[54.526,-83.122],[-8.097,-81.603],[-8.897,-82.289],[-8.187,-83.063],[54.511,-84.582],[55.794,-84.582],[133.888,-80.318],[134.537,-79.5],[133.797,-78.858]],"i":[[0.377,0],[0.046,0],[32.753,0],[0.211,0],[0,0],[27.531,-1.489],[0.031,0.394],[-0.408,0.029],[-19.621,0.015],[0,0],[-15.35,-1.986],[0.06,-0.395],[0.377,0]],"o":[[-0.03,0],[-15.199,-1.971],[-0.226,0],[0,0],[-19.606,0.015],[-0.437,0.058],[-0.03,-0.409],[27.561,-1.49],[0,0],[33.025,-0.029],[0.407,0.058],[-0.046,0.379],[-0.03,0]]}}},{"ty":"fl","c":{"a":0,"k":[0.17647058823529413,0.4470588235294118,0.6745098039215687],"ix":2},"o":{"a":0,"k":100,"ix":2},"r":1,"bm":0,"nm":"Fill 1","mn":"ADBE Vector Graphic - Fill","hd":false},{"ty":"tm","s":{"a":0,"k":0,"ix":2},"e":{"a":0,"k":100,"ix":2},"o":{"a":0,"k":0,"ix":2},"m":1,"hd":false},{"ty":"tr","hd":false,"p":{"a":0,"k":[0,0],"ix":2},"a":{"a":0,"k":[0,0],"ix":2},"s":{"a":0,"k":[100,100],"ix":2},"r":{"a":0,"k":0,"ix":2},"o":{"a":0,"k":100,"ix":2},"sk":{"a":0,"k":0,"ix":2},"sa":{"a":0,"k":0,"ix":2}}]}],"ip":0,"op":400,"st":0,"bm":0},{"ddd":0,"ind":24,"ty":4,"nm":"Group 2","sr":1,"ks":{"o":{"a":0,"k":100,"ix":2},"r":{"a":0,"k":0,"ix":2},"p":{"a":0,"k":[0,0],"ix":2},"a":{"a":0,"k":[0,0],"ix":2},"s":{"a":0,"k":[100,100],"ix":2}},"ao":0,"hd":false,"parent":2,"shapes":[{"ty":"gr","hd":false,"it":[{"ty":"sh","hd":false,"d":1,"ks":{"a":0,"k":{"c":false,"v":[[428.6,-35.986],[427.921,-36.41],[415.711,-38.074],[414.775,-38.556],[415.273,-39.462],[429.28,-37.023],[428.917,-36.045],[428.6,-35.986]],"i":[[0.106,0],[0.121,0.263],[1.931,-0.555],[0.12,0.379],[-0.393,0.117],[-1.993,-4.059],[0.378,-0.175],[0.106,0]],"o":[[-0.286,0],[-1.343,-2.745],[-0.393,0.116],[-0.121,-0.38],[1.6,-0.467],[0.181,0.365],[-0.09,0.029],[-0.286,0]]}}},{"ty":"fl","c":{"a":0,"k":[0.17647058823529413,0.4470588235294118,0.6745098039215687],"ix":2},"o":{"a":0,"k":100,"ix":2},"r":1,"bm":0,"nm":"Fill 1","mn":"ADBE Vector Graphic - Fill","hd":false},{"ty":"tm","s":{"a":0,"k":0,"ix":2},"e":{"a":0,"k":100,"ix":2},"o":{"a":0,"k":0,"ix":2},"m":1,"hd":false},{"ty":"tr","hd":false,"p":{"a":0,"k":[0,0],"ix":2},"a":{"a":0,"k":[0,0],"ix":2},"s":{"a":0,"k":[100,100],"ix":2},"r":{"a":0,"k":0,"ix":2},"o":{"a":0,"k":100,"ix":2},"sk":{"a":0,"k":0,"ix":2},"sa":{"a":0,"k":0,"ix":2}}]}],"ip":0,"op":400,"st":0,"bm":0},{"ddd":0,"ind":25,"ty":4,"nm":"Group 3","sr":1,"ks":{"o":{"a":0,"k":100,"ix":2},"r":{"a":0,"k":0,"ix":2},"p":{"a":0,"k":[0,0],"ix":2},"a":{"a":0,"k":[0,0],"ix":2},"s":{"a":0,"k":[100,100],"ix":2}},"ao":0,"hd":false,"parent":2,"shapes":[{"ty":"gr","hd":false,"it":[{"ty":"sh","hd":false,"d":1,"ks":{"a":0,"k":{"c":false,"v":[[424.736,-25.928],[424.012,-26.468],[422.382,-28.498],[414.895,-28.118],[413.93,-28.541],[414.367,-29.476],[423.091,-29.797],[425.476,-26.848],[424.933,-25.957],[424.736,-25.928]],"i":[[0.061,0],[0.091,0.321],[0.845,0.424],[0.046,-0.015],[0.135,0.379],[-0.392,0.131],[-3.305,-1.636],[-0.362,-1.343],[0.407,-0.102],[0.061,0]],"o":[[-0.332,0],[-0.257,-0.949],[-2.702,-1.343],[-0.392,0.146],[-0.136,-0.38],[0.227,-0.073],[1.223,0.613],[0.106,0.395],[-0.061,0.015],[-0.332,0]]}}},{"ty":"fl","c":{"a":0,"k":[0.17647058823529413,0.4470588235294118,0.6745098039215687],"ix":2},"o":{"a":0,"k":100,"ix":2},"r":1,"bm":0,"nm":"Fill 1","mn":"ADBE Vector Graphic - Fill","hd":false},{"ty":"tm","s":{"a":0,"k":0,"ix":2},"e":{"a":0,"k":100,"ix":2},"o":{"a":0,"k":0,"ix":2},"m":1,"hd":false},{"ty":"tr","hd":false,"p":{"a":0,"k":[0,0],"ix":2},"a":{"a":0,"k":[0,0],"ix":2},"s":{"a":0,"k":[100,100],"ix":2},"r":{"a":0,"k":0,"ix":2},"o":{"a":0,"k":100,"ix":2},"sk":{"a":0,"k":0,"ix":2},"sa":{"a":0,"k":0,"ix":2}}]}],"ip":0,"op":400,"st":0,"bm":0},{"ddd":0,"ind":26,"ty":4,"nm":"Group 4","sr":1,"ks":{"o":{"a":0,"k":100,"ix":2},"r":{"a":0,"k":0,"ix":2},"p":{"a":0,"k":[0,0],"ix":2},"a":{"a":0,"k":[0,0],"ix":2},"s":{"a":0,"k":[100,100],"ix":2}},"ao":0,"hd":false,"parent":2,"shapes":[{"ty":"gr","hd":false,"it":[{"ty":"gr","hd":false,"it":[{"ty":"sh","hd":false,"d":1,"ks":{"a":0,"k":{"c":false,"v":[[18.181,-115.378],[55.809,-83.853],[-8.127,-82.334],[18.181,-115.378]],"i":[[0,0],[0,0],[19.319,-0.92],[0,0]],"o":[[0,0],[-22.475,-0.073],[0,0],[0,0]]}}},{"ty":"tm","s":{"a":0,"k":0,"ix":2},"e":{"a":0,"k":100,"ix":2},"o":{"a":0,"k":0,"ix":2},"m":1,"hd":false},{"ty":"tr","hd":false,"p":{"a":0,"k":[0,0],"ix":2},"a":{"a":0,"k":[0,0],"ix":2},"s":{"a":0,"k":[100,100],"ix":2},"r":{"a":0,"k":0,"ix":2},"o":{"a":0,"k":100,"ix":2},"sk":{"a":0,"k":0,"ix":2},"sa":{"a":0,"k":0,"ix":2}}]},{"ty":"gr","hd":false,"it":[{"ty":"sh","hd":false,"d":1,"ks":{"a":0,"k":{"c":false,"v":[[-236.16,-40.076],[-176.042,-8.755],[88.32,-28.891],[355.761,-3.542],[375.413,5.409],[424.738,-26.657],[428.602,-36.718],[431.289,-44.544],[409.328,-48.283],[353.829,-51.626],[133.796,-79.589],[44.775,-186.781],[-26.904,-192.929],[-53.846,-168.252],[-73.15,-176.37],[-177.204,-158.264],[-242.755,-157.884],[-290.692,-118.182],[-302.939,-78.725]],"i":[[6.943,48.463],[-22.731,-21.261],[-139.117,-4.848],[0,0],[-15.033,5.212],[1.54,9.33],[3.079,6.337],[2.702,7.081],[5.781,-1.489],[35.847,8.571],[31.214,1.489],[36.994,30.897],[30.051,-26.838],[5.751,-5.461],[7.32,2.117],[17.734,-2.979],[11.516,7.461],[11.742,-24.794],[3.645,-16.868]],"o":[[0,0],[0,0],[139.116,4.848],[0,0],[15.033,-5.213],[0,0],[0,0],[-2.687,-7.082],[-5.781,1.504],[-35.832,-8.586],[0,0],[-15.033,-12.558],[-12.603,11.243],[-5.448,-3.285],[-25.055,-7.243],[-17.72,2.994],[-11.517,-7.462],[-4.166,8.796],[-6.63,30.677]]}}},{"ty":"tm","s":{"a":0,"k":0,"ix":2},"e":{"a":0,"k":100,"ix":2},"o":{"a":0,"k":0,"ix":2},"m":1,"hd":false},{"ty":"tr","hd":false,"p":{"a":0,"k":[0,0],"ix":2},"a":{"a":0,"k":[0,0],"ix":2},"s":{"a":0,"k":[100,100],"ix":2},"r":{"a":0,"k":0,"ix":2},"o":{"a":0,"k":100,"ix":2},"sk":{"a":0,"k":0,"ix":2},"sa":{"a":0,"k":0,"ix":2}}]},{"ty":"fl","c":{"a":0,"k":[0.5019607843137255,0.7725490196078432,1],"ix":2},"o":{"a":0,"k":100,"ix":2},"r":1,"bm":0,"nm":"Fill 1","mn":"ADBE Vector Graphic - Fill","hd":false},{"ty":"tr","hd":false,"p":{"a":0,"k":[0,0],"ix":2},"a":{"a":0,"k":[0,0],"ix":2},"s":{"a":0,"k":[100,100],"ix":2},"r":{"a":0,"k":0,"ix":2},"o":{"a":0,"k":100,"ix":2},"sk":{"a":0,"k":0,"ix":2},"sa":{"a":0,"k":0,"ix":2}}]}],"ip":0,"op":400,"st":0,"bm":0},{"ddd":0,"ind":27,"ty":4,"nm":"Group 4","sr":1,"ks":{"o":{"a":0,"k":100,"ix":2},"r":{"a":0,"k":0,"ix":2},"p":{"a":0,"k":[0,0],"ix":2},"a":{"a":0,"k":[0,0],"ix":2},"s":{"a":0,"k":[100,100],"ix":2}},"ao":0,"hd":false,"parent":2,"shapes":[{"ty":"gr","hd":false,"it":[{"ty":"gr","hd":false,"it":[{"ty":"sh","hd":false,"d":1,"ks":{"a":0,"k":{"c":false,"v":[[-6.542,-83.152],[18.287,-114.327],[53.772,-84.598],[-6.542,-83.152]],"i":[[21.177,-0.979],[0,0],[0,0],[21.177,-0.979]],"o":[[0,0],[0,0],[-18.867,-0.073],[0,0]]}}},{"ty":"tm","s":{"a":0,"k":0,"ix":2},"e":{"a":0,"k":100,"ix":2},"o":{"a":0,"k":0,"ix":2},"m":1,"hd":false},{"ty":"tr","hd":false,"p":{"a":0,"k":[0,0],"ix":2},"a":{"a":0,"k":[0,0],"ix":2},"s":{"a":0,"k":[100,100],"ix":2},"r":{"a":0,"k":0,"ix":2},"o":{"a":0,"k":100,"ix":2},"sk":{"a":0,"k":0,"ix":2},"sa":{"a":0,"k":0,"ix":2}}]},{"ty":"gr","hd":false,"it":[{"ty":"sh","hd":false,"d":1,"ks":{"a":0,"k":{"c":false,"v":[[56.323,-84.408],[18.695,-115.934],[18.121,-116.109],[17.593,-115.831],[-8.715,-82.787],[-8.791,-81.999],[-8.126,-81.605],[-8.066,-81.619],[55.825,-83.138],[56.534,-83.605],[56.323,-84.408]],"i":[[0.241,0.204],[0,0],[0.196,-0.029],[0.121,-0.161],[0,0],[-0.135,-0.248],[-0.287,0],[-0.03,0.014],[-19.879,-0.087],[-0.106,0.292],[0.241,0.204]],"o":[[0,0],[-0.166,-0.131],[-0.211,0.015],[0,0],[-0.181,0.233],[0.121,0.248],[0.015,0],[22.504,-1.066],[0.317,0],[0.106,-0.278],[0,0]]}}},{"ty":"tm","s":{"a":0,"k":0,"ix":2},"e":{"a":0,"k":100,"ix":2},"o":{"a":0,"k":0,"ix":2},"m":1,"hd":false},{"ty":"tr","hd":false,"p":{"a":0,"k":[0,0],"ix":2},"a":{"a":0,"k":[0,0],"ix":2},"s":{"a":0,"k":[100,100],"ix":2},"r":{"a":0,"k":0,"ix":2},"o":{"a":0,"k":100,"ix":2},"sk":{"a":0,"k":0,"ix":2},"sa":{"a":0,"k":0,"ix":2}}]},{"ty":"fl","c":{"a":0,"k":[0.17647058823529413,0.4470588235294118,0.6745098039215687],"ix":2},"o":{"a":0,"k":100,"ix":2},"r":1,"bm":0,"nm":"Fill 1","mn":"ADBE Vector Graphic - Fill","hd":false},{"ty":"tr","hd":false,"p":{"a":0,"k":[0,0],"ix":2},"a":{"a":0,"k":[0,0],"ix":2},"s":{"a":0,"k":[100,100],"ix":2},"r":{"a":0,"k":0,"ix":2},"o":{"a":0,"k":100,"ix":2},"sk":{"a":0,"k":0,"ix":2},"sa":{"a":0,"k":0,"ix":2}}]}],"ip":0,"op":400,"st":0,"bm":0},{"ddd":0,"ind":28,"ty":4,"nm":"Group 1","sr":1,"ks":{"o":{"a":0,"k":100,"ix":2},"r":{"a":0,"k":0,"ix":2},"p":{"a":0,"k":[0,0],"ix":2},"a":{"a":0,"k":[0,0],"ix":2},"s":{"a":0,"k":[100,100],"ix":2}},"ao":0,"hd":false,"shapes":[{"ty":"gr","hd":false,"it":[{"ty":"sh","hd":false,"d":1,"ks":{"a":0,"k":{"c":false,"v":[[262.125,191.819],[459.426,76.245],[363.855,-83.865],[239.771,-199.073],[-87.018,-260.781],[-350.61,-87.048],[-463.464,93.388],[-201.864,191.804],[262.125,191.819]],"i":[[0,0],[-36.918,110.127],[92.523,44.2],[43.832,40.053],[165.244,-14.996],[45.145,-36.183],[-13.101,-84.998],[-172.639,1.504],[0,0]],"o":[[51.634,0],[18.505,-55.181],[-93.263,-44.565],[-55.498,-50.698],[-213.497,19.391],[-74.38,59.62],[13.101,84.997],[172.654,-1.475],[51.634,0]]}}},{"ty":"fl","c":{"a":0,"k":[0.3411764705882353,0.396078431372549,0.8196078431372549],"ix":2},"o":{"a":0,"k":100,"ix":2},"r":1,"bm":0,"nm":"Fill 1","mn":"ADBE Vector Graphic - Fill","hd":false},{"ty":"tm","s":{"a":0,"k":0,"ix":2},"e":{"a":0,"k":100,"ix":2},"o":{"a":0,"k":0,"ix":2},"m":1,"hd":false},{"ty":"tr","hd":false,"p":{"a":0,"k":[255.6958465576172,243.6718444824219],"ix":2},"a":{"a":0,"k":[0,0],"ix":2},"s":{"a":0,"k":[51.99999809265137,51.99999809265137],"ix":2},"r":{"a":0,"k":0,"ix":2},"o":{"a":0,"k":100,"ix":2},"sk":{"a":0,"k":0,"ix":2},"sa":{"a":0,"k":0,"ix":2}}]}],"ip":0,"op":400,"st":0,"bm":0}],"markers":[]}